{"version": 0.6, "generator": "Overpass API 0.7.62.4 2390de5a", "osm3s": {"timestamp_osm_base": "2025-01-03T15:27:15Z", "copyright": "The data included in this document is from www.openstreetmap.org. The data is made available under ODbL."}, "elements": [{"type": "node", "id": 46122858, "lat": 52.309523, "lon": 4.7621813, "tags": {"name": "Schiphol Airport", "public_transport": "station", "railway": "station", "railway:ref": "Shl", "toilets:wheelchair": "yes", "train": "yes", "uic_ref": "8400561", "website": "https://www.ns.nl/en/station-information/shl/schiphol-airport", "wheelchair": "yes", "wikidata": "Q801410", "wikipedia": "nl:Station Schiphol Airport", "zone": "5733"}}, {"type": "node", "id": 46199966, "lat": 52.3302613, "lon": 4.9560598, "tags": {"name": "Diemen Zuid", "network": "Hoofdrailnet Nederland;Amsterdamse metro", "network:subway": "Amsterdamse metro", "network:train": "Hoofdrailnet Nederland", "operator": "Nederlandse Spoorwegen;GVB", "operator:subway": "GVB", "operator:train": "Nederlandse Spoorwegen", "public_transport": "station", "railway": "station", "railway:ref": "Dmnz", "source": "AND", "start_date": "1977-10-14", "station": "train;subway", "subway": "yes", "train": "yes", "website": "https://9292.nl/en/station-diemen-zuid", "wheelchair": "no", "wikidata": "Q800664", "wikimedia_commons": "Category:Station Diemen Zuid", "wikipedia": "nl:Station Diemen Zuid", "zone": "5715"}}, {"type": "node", "id": 250222266, "lat": 52.3384028, "lon": 4.8575769, "tags": {"name": "Amstelveenseweg", "network": "Amsterdamse metro", "operator": "GVB", "public_transport": "station", "railway": "station", "start_date": "1997-05-18", "station": "subway", "subway": "yes", "website": "https://9292.nl/en/amsterdam/metrostation-amstelveenseweg", "wheelchair": "yes", "wikidata": "Q1846380", "wikimedia_commons": "Category:Metrostation Amstelveenseweg", "wikipedia": "nl:Amstelveenseweg (metrostation)", "zone": "5714"}}, {"type": "node", "id": 250224485, "lat": 52.3726582, "lon": 4.8352937, "tags": {"name": "Jan van Galenstraat", "network": "Amsterdamse metro", "operator": "GVB", "public_transport": "station", "railway": "station", "start_date": "1997-05-28", "station": "subway", "subway": "yes", "wheelchair": "yes", "wikidata": "Q3273303", "wikipedia": "nl:Jan van Galenstraat (metrostation)", "zone": "5713"}}, {"type": "node", "id": 250233810, "lat": 52.2979886, "lon": 4.9601712, "tags": {"loc_name": "Holendrecht", "name": "Amsterdam Holendrecht", "network": "Hoofdrailnet Nederland;Amsterdamse metro", "network:subway": "Amsterdamse metro", "network:train": "Hoofdrailnet Nederland", "operator": "Nederlandse Spoorwegen;GVB", "operator:subway": "GVB", "operator:train": "Nederlandse Spoorwegen", "public_transport": "station", "railway": "station", "railway:ref": "Ashd", "start_date": "1977-10-14", "start_date:train": "2008-12-14", "station": "train;subway", "subway": "yes", "train": "yes", "wheelchair": "yes", "wikidata": "Q800381", "wikimedia_commons": "Category:Station Amsterdam Holendrecht", "wikipedia": "nl:Station Amsterdam Holendrecht", "zone": "5725"}}, {"type": "node", "id": 289445435, "lat": 52.3294483, "lon": 4.9305189, "tags": {"name": "Van der Madeweg", "network": "Amsterdamse metro", "operator": "GVB", "public_transport": "station", "railway": "station", "start_date": "1977-10-14", "station": "subway", "subway": "yes", "wheelchair": "yes", "wikidata": "Q7913863", "wikimedia_commons": "Category:Metrostation Van der Madeweg", "wikipedia": "nl:Van der Madeweg (metrostation)", "zone": "5715"}}, {"type": "node", "id": 427565080, "lat": 52.3317318, "lon": 4.9176266, "tags": {"layer": "1", "name": "Overamstel", "network": "Amsterdamse metro", "operator": "GVB", "public_transport": "station", "railway": "station", "start_date": "1990-12-01", "station": "subway", "subway": "yes", "wheelchair": "yes", "wikidata": "Q3371836", "wikimedia_commons": "Category:Metrostation Overamstel", "wikipedia": "nl:Overamstel (metrostation)", "zone": "5715"}}, {"type": "node", "id": 1633149045, "lat": 52.3859763, "lon": 4.7468736, "tags": {"name": "Halfweg-Zwanenburg", "operator": "Nederlandse Spoorwegen", "platforms": "2", "public_transport": "station", "railway": "station", "railway:ref": "Hwzb", "start_date": "2012-12-09", "train": "yes", "wheelchair": "yes", "wikidata": "Q2272349", "wikipedia": "nl:Station Halfweg-Zwanenburg"}}, {"type": "node", "id": 2237721918, "lat": 52.3796134, "lon": 4.8382223, "tags": {"name": "De Vlugtlaan", "network": "Amsterdamse metro", "operator": "GVB", "public_transport": "station", "railway": "station", "start_date": "1997-05-28", "station": "subway", "subway": "yes", "website": "https://9292.nl/en/amsterdam/metrostation-burg-de-vlugtlaan", "wheelchair": "yes", "wikidata": "Q2061210", "wikimedia_commons": "Category:Metrostation De Vlugtlaan", "wikipedia": "nl:De Vlugtlaan (metrostation)"}}, {"type": "node", "id": 2724002225, "lat": 52.3693417, "lon": 4.8925344}, {"type": "node", "id": 2724002236, "lat": 52.3693615, "lon": 4.8922922}, {"type": "node", "id": 2724002244, "lat": 52.3693632, "lon": 4.8922713}, {"type": "node", "id": 2724002257, "lat": 52.3693853, "lon": 4.8920019}, {"type": "node", "id": 2724002259, "lat": 52.3693858, "lon": 4.8919958}, {"type": "node", "id": 2724002359, "lat": 52.3694628, "lon": 4.8926345}, {"type": "node", "id": 2724002497, "lat": 52.3695971, "lon": 4.8920876}, {"type": "node", "id": 2724002498, "lat": 52.3695981, "lon": 4.8920619}, {"type": "node", "id": 2724002515, "lat": 52.3696241, "lon": 4.8926568}, {"type": "node", "id": 2724002516, "lat": 52.3696245, "lon": 4.8926524}, {"type": "node", "id": 2724002623, "lat": 52.3698008, "lon": 4.892139}, {"type": "node", "id": 2724002690, "lat": 52.3699174, "lon": 4.8921767}, {"type": "node", "id": 2724002697, "lat": 52.3699259, "lon": 4.8922311}, {"type": "node", "id": 2724002705, "lat": 52.3699695, "lon": 4.892725}, {"type": "node", "id": 2724002844, "lat": 52.3703151, "lon": 4.8923395}, {"type": "node", "id": 2724002849, "lat": 52.370329, "lon": 4.8928081}, {"type": "node", "id": 2724002903, "lat": 52.370389, "lon": 4.8928495}, {"type": "node", "id": 2724002939, "lat": 52.3704275, "lon": 4.8924361}, {"type": "node", "id": 2724003266, "lat": 52.3706376, "lon": 4.8929049}, {"type": "node", "id": 2724003394, "lat": 52.3706862, "lon": 4.8928876}, {"type": "node", "id": 2724003506, "lat": 52.3707536, "lon": 4.892508}, {"type": "node", "id": 2724003678, "lat": 52.3709938, "lon": 4.8929524}, {"type": "node", "id": 2724003683, "lat": 52.3710067, "lon": 4.8925665}, {"type": "node", "id": 2724003710, "lat": 52.3710875, "lon": 4.8925985}, {"type": "node", "id": 2724003791, "lat": 52.3711524, "lon": 4.8929861}, {"type": "node", "id": 2724003898, "lat": 52.3712916, "lon": 4.8930461}, {"type": "node", "id": 2724003901, "lat": 52.3712938, "lon": 4.8930074}, {"type": "node", "id": 2724004020, "lat": 52.3714019, "lon": 4.8926397}, {"type": "node", "id": 2724004022, "lat": 52.3714021, "lon": 4.8926353}, {"type": "node", "id": 2724004095, "lat": 52.3715351, "lon": 4.8930982}, {"type": "node", "id": 2724004150, "lat": 52.3715621, "lon": 4.8931243}, {"type": "node", "id": 2724004202, "lat": 52.3716074, "lon": 4.8928103}, {"type": "node", "id": 2724004222, "lat": 52.3716182, "lon": 4.8926605}, {"type": "node", "id": 2724004294, "lat": 52.3717067, "lon": 4.8929529}, {"type": "node", "id": 2724004340, "lat": 52.3717474, "lon": 4.8931639}, {"type": "node", "id": 2724004341, "lat": 52.3717515, "lon": 4.8931129}, {"type": "node", "id": 2724004383, "lat": 52.3718375, "lon": 4.8931313}, {"type": "node", "id": 2724004400, "lat": 52.3718515, "lon": 4.892956}, {"type": "node", "id": 2741068312, "lat": 52.3670121, "lon": 4.9024932}, {"type": "node", "id": 2741068324, "lat": 52.3670201, "lon": 4.9028383}, {"type": "node", "id": 2741068383, "lat": 52.3670512, "lon": 4.9024132}, {"type": "node", "id": 2741068392, "lat": 52.3670755, "lon": 4.9024451}, {"type": "node", "id": 2741068396, "lat": 52.3670889, "lon": 4.9024171}, {"type": "node", "id": 2741068405, "lat": 52.3671132, "lon": 4.902449}, {"type": "node", "id": 2741068406, "lat": 52.3671136, "lon": 4.902625}, {"type": "node", "id": 2741068410, "lat": 52.3671224, "lon": 4.9024296}, {"type": "node", "id": 2741068412, "lat": 52.3671244, "lon": 4.9026022}, {"type": "node", "id": 2741068425, "lat": 52.3671366, "lon": 4.9030094}, {"type": "node", "id": 2741068427, "lat": 52.3671394, "lon": 4.9026208}, {"type": "node", "id": 2741068464, "lat": 52.3671935, "lon": 4.9025221}, {"type": "node", "id": 2741068528, "lat": 52.3672527, "lon": 4.9027952}, {"type": "node", "id": 2741068535, "lat": 52.3672749, "lon": 4.9020476}, {"type": "node", "id": 2741068546, "lat": 52.367323, "lon": 4.9019305}, {"type": "node", "id": 2741068574, "lat": 52.3673745, "lon": 4.9019869}, {"type": "node", "id": 2741068580, "lat": 52.3673867, "lon": 4.90217}, {"type": "node", "id": 2741068589, "lat": 52.3674019, "lon": 4.9019192}, {"type": "node", "id": 2741068607, "lat": 52.3674639, "lon": 4.9020569}, {"type": "node", "id": 2741068626, "lat": 52.3674822, "lon": 4.9020128}, {"type": "node", "id": 2741068649, "lat": 52.3675111, "lon": 4.9023227}, {"type": "node", "id": 2741068651, "lat": 52.3675222, "lon": 4.9023703}, {"type": "node", "id": 2741068654, "lat": 52.3675322, "lon": 4.902346}, {"type": "node", "id": 2741068657, "lat": 52.3675838, "lon": 4.9021981}, {"type": "node", "id": 2741068658, "lat": 52.3675923, "lon": 4.9022471}, {"type": "node", "id": 2741068660, "lat": 52.3676031, "lon": 4.9021536}, {"type": "node", "id": 2741068664, "lat": 52.3676238, "lon": 4.9021799}, {"type": "node", "id": 2741068665, "lat": 52.367647, "lon": 4.9023168}, {"type": "node", "id": 2741068671, "lat": 52.3676902, "lon": 4.9023589}, {"type": "node", "id": 2741068673, "lat": 52.3677123, "lon": 4.9025795}, {"type": "node", "id": 2741068678, "lat": 52.3677546, "lon": 4.9024296}, {"type": "node", "id": 2741068680, "lat": 52.367768, "lon": 4.9024444}, {"type": "node", "id": 2742813460, "lat": 52.3606746, "lon": 4.9081688}, {"type": "node", "id": 2742813471, "lat": 52.3606925, "lon": 4.9079932}, {"type": "node", "id": 2742813501, "lat": 52.3607262, "lon": 4.9081364}, {"type": "node", "id": 2742813506, "lat": 52.3607276, "lon": 4.9084057}, {"type": "node", "id": 2742813508, "lat": 52.3607282, "lon": 4.9079215}, {"type": "node", "id": 2742813509, "lat": 52.3607382, "lon": 4.9079659}, {"type": "node", "id": 2742813517, "lat": 52.36076, "lon": 4.9079027}, {"type": "node", "id": 2742813526, "lat": 52.360782, "lon": 4.9083716}, {"type": "node", "id": 2742813537, "lat": 52.3608035, "lon": 4.9080878}, {"type": "node", "id": 2742813538, "lat": 52.3608037, "lon": 4.9080548}, {"type": "node", "id": 2742813545, "lat": 52.3608106, "lon": 4.9080833}, {"type": "node", "id": 2742813574, "lat": 52.3608419, "lon": 4.908625}, {"type": "node", "id": 2742813602, "lat": 52.3608596, "lon": 4.9083229}, {"type": "node", "id": 2742813608, "lat": 52.3608643, "lon": 4.90832}, {"type": "node", "id": 2742813620, "lat": 52.3608709, "lon": 4.9083464}, {"type": "node", "id": 2742813672, "lat": 52.3609173, "lon": 4.9085664}, {"type": "node", "id": 2742813673, "lat": 52.3609175, "lon": 4.9085773}, {"type": "node", "id": 2742813678, "lat": 52.3609195, "lon": 4.9085858}, {"type": "node", "id": 2742813681, "lat": 52.3609214, "lon": 4.9085827}, {"type": "node", "id": 2742813727, "lat": 52.360973, "lon": 4.9083002}, {"type": "node", "id": 2742813765, "lat": 52.3610093, "lon": 4.908456}, {"type": "node", "id": 2742813775, "lat": 52.3610224, "lon": 4.9084481}, {"type": "node", "id": 2742813777, "lat": 52.3610244, "lon": 4.9085228}, {"type": "node", "id": 2742813779, "lat": 52.3610259, "lon": 4.9085272}, {"type": "node", "id": 2742813782, "lat": 52.3610287, "lon": 4.9085392}, {"type": "node", "id": 2742813791, "lat": 52.3610366, "lon": 4.9082394}, {"type": "node", "id": 2742813792, "lat": 52.3610375, "lon": 4.9085149}, {"type": "node", "id": 2742813796, "lat": 52.3610408, "lon": 4.9082591}, {"type": "node", "id": 2742813814, "lat": 52.3610596, "lon": 4.9077808}, {"type": "node", "id": 2742813843, "lat": 52.3610817, "lon": 4.9078784}, {"type": "node", "id": 2742813885, "lat": 52.3610956, "lon": 4.9082013}, {"type": "node", "id": 2742813911, "lat": 52.3611112, "lon": 4.9075052}, {"type": "node", "id": 2742813925, "lat": 52.3611222, "lon": 4.9083126}, {"type": "node", "id": 2742813933, "lat": 52.3611279, "lon": 4.9075856}, {"type": "node", "id": 2742813936, "lat": 52.3611292, "lon": 4.9075894}, {"type": "node", "id": 2742813941, "lat": 52.3611309, "lon": 4.9075929}, {"type": "node", "id": 2742813945, "lat": 52.361133, "lon": 4.9075957}, {"type": "node", "id": 2742813950, "lat": 52.3611354, "lon": 4.9075978}, {"type": "node", "id": 2742813954, "lat": 52.3611373, "lon": 4.9083697}, {"type": "node", "id": 2742813956, "lat": 52.361138, "lon": 4.9075991}, {"type": "node", "id": 2742813957, "lat": 52.3611383, "lon": 4.9074903}, {"type": "node", "id": 2742813961, "lat": 52.3611407, "lon": 4.9075996}, {"type": "node", "id": 2742813965, "lat": 52.3611434, "lon": 4.9075993}, {"type": "node", "id": 2742813969, "lat": 52.3611454, "lon": 4.9075985}, {"type": "node", "id": 2742813975, "lat": 52.361149, "lon": 4.9075421}, {"type": "node", "id": 2742813976, "lat": 52.3611501, "lon": 4.9081662}, {"type": "node", "id": 2742813977, "lat": 52.3611505, "lon": 4.9075461}, {"type": "node", "id": 2742813981, "lat": 52.361152, "lon": 4.907548}, {"type": "node", "id": 2742813983, "lat": 52.3611546, "lon": 4.9075494}, {"type": "node", "id": 2742813989, "lat": 52.3611565, "lon": 4.9075493}, {"type": "node", "id": 2742813991, "lat": 52.361159, "lon": 4.9084607}, {"type": "node", "id": 2742814005, "lat": 52.361164, "lon": 4.908355}, {"type": "node", "id": 2742814073, "lat": 52.3611749, "lon": 4.9082664}, {"type": "node", "id": 2742814079, "lat": 52.3611764, "lon": 4.9083615}, {"type": "node", "id": 2742814128, "lat": 52.3611856, "lon": 4.9083969}, {"type": "node", "id": 2742814184, "lat": 52.3611991, "lon": 4.9075687}, {"type": "node", "id": 2742814202, "lat": 52.3612014, "lon": 4.9075685}, {"type": "node", "id": 2742814210, "lat": 52.3612024, "lon": 4.90827}, {"type": "node", "id": 2742814222, "lat": 52.3612037, "lon": 4.907569}, {"type": "node", "id": 2742814232, "lat": 52.3612058, "lon": 4.907522}, {"type": "node", "id": 2742814235, "lat": 52.3612058, "lon": 4.9075704}, {"type": "node", "id": 2742814241, "lat": 52.3612077, "lon": 4.9075725}, {"type": "node", "id": 2742814244, "lat": 52.3612096, "lon": 4.907576}, {"type": "node", "id": 2742814247, "lat": 52.3612103, "lon": 4.9075792}, {"type": "node", "id": 2742814253, "lat": 52.3612105, "lon": 4.9075945}, {"type": "node", "id": 2742814262, "lat": 52.3612113, "lon": 4.9076046}, {"type": "node", "id": 2742814268, "lat": 52.3612125, "lon": 4.9075232}, {"type": "node", "id": 2742814290, "lat": 52.3612171, "lon": 4.9075249}, {"type": "node", "id": 2742814308, "lat": 52.3612217, "lon": 4.9075275}, {"type": "node", "id": 2742814310, "lat": 52.3612255, "lon": 4.9083757}, {"type": "node", "id": 2742814315, "lat": 52.361228, "lon": 4.9076742}, {"type": "node", "id": 2742814321, "lat": 52.3612296, "lon": 4.9075335}, {"type": "node", "id": 2742814324, "lat": 52.3612337, "lon": 4.9075356}, {"type": "node", "id": 2742814332, "lat": 52.361238, "lon": 4.9075368}, {"type": "node", "id": 2742814338, "lat": 52.3612445, "lon": 4.9075368}, {"type": "node", "id": 2742814540, "lat": 52.3613436, "lon": 4.9073455}, {"type": "node", "id": 2742814629, "lat": 52.3613633, "lon": 4.9074706}, {"type": "node", "id": 2742814640, "lat": 52.3613655, "lon": 4.9074683}, {"type": "node", "id": 2742814993, "lat": 52.3613669, "lon": 4.9074649}, {"type": "node", "id": 2742814997, "lat": 52.3613671, "lon": 4.9074579}, {"type": "node", "id": 2742815001, "lat": 52.3613674, "lon": 4.9074608}, {"type": "node", "id": 2742815082, "lat": 52.3613829, "lon": 4.9073239}, {"type": "node", "id": 2742815177, "lat": 52.361399, "lon": 4.9074034}, {"type": "node", "id": 2742815411, "lat": 52.3614734, "lon": 4.9073618}, {"type": "node", "id": 2742815421, "lat": 52.3614751, "lon": 4.9073702}, {"type": "node", "id": 2742815426, "lat": 52.3614763, "lon": 4.9073741}, {"type": "node", "id": 2742815434, "lat": 52.3614777, "lon": 4.9073768}, {"type": "node", "id": 2742815439, "lat": 52.3614786, "lon": 4.9073779}, {"type": "node", "id": 2742815443, "lat": 52.3614795, "lon": 4.9073789}, {"type": "node", "id": 2742815455, "lat": 52.3614814, "lon": 4.9073802}, {"type": "node", "id": 2742815479, "lat": 52.3614835, "lon": 4.9073808}, {"type": "node", "id": 2742815488, "lat": 52.3614857, "lon": 4.9073806}, {"type": "node", "id": 2742815531, "lat": 52.3614972, "lon": 4.9073744}, {"type": "node", "id": 2742815583, "lat": 52.3615067, "lon": 4.9074515}, {"type": "node", "id": 2742815587, "lat": 52.3615067, "lon": 4.9074562}, {"type": "node", "id": 2742815591, "lat": 52.3615074, "lon": 4.9074485}, {"type": "node", "id": 2742815610, "lat": 52.3615093, "lon": 4.907445}, {"type": "node", "id": 2742815618, "lat": 52.3615111, "lon": 4.9074435}, {"type": "node", "id": 2742815627, "lat": 52.3615139, "lon": 4.9080504}, {"type": "node", "id": 2742815661, "lat": 52.3615256, "lon": 4.9080521}, {"type": "node", "id": 2742815680, "lat": 52.3615374, "lon": 4.9075869}, {"type": "node", "id": 2742815748, "lat": 52.3615642, "lon": 4.9080221}, {"type": "node", "id": 2742815750, "lat": 52.3615657, "lon": 4.9080296}, {"type": "node", "id": 2742815816, "lat": 52.3615818, "lon": 4.908012}, {"type": "node", "id": 2742815845, "lat": 52.3615879, "lon": 4.9080425}, {"type": "node", "id": 2742816181, "lat": 52.3616002, "lon": 4.9078815}, {"type": "node", "id": 2742816225, "lat": 52.3616094, "lon": 4.9080289}, {"type": "node", "id": 2742816228, "lat": 52.3616102, "lon": 4.908033}, {"type": "node", "id": 2742816312, "lat": 52.3616257, "lon": 4.907531}, {"type": "node", "id": 2742816349, "lat": 52.3616322, "lon": 4.9080236}, {"type": "node", "id": 2742816574, "lat": 52.3616949, "lon": 4.9078216}, {"type": "node", "id": 3187687707, "lat": 52.3716466, "lon": 4.8928643}, {"type": "node", "id": 3938547498, "lat": 52.3890317, "lon": 4.8381062, "tags": {"name": "Amsterdam Sloterdijk", "network": "Hoofdrailnet Nederland", "network:short": "HRN", "network:wikidata": "Q2337464", "network:wikipedia": "nl:Hoofdrailnet", "operator": "Nederlandse Spoorwegen", "public_transport": "station", "railway": "station", "railway:ref": "Ass", "start_date": "1983-05-29", "train": "yes", "wheelchair": "yes", "wikidata": "Q50721", "wikipedia": "nl:Station Amsterdam Sloterdijk"}}, {"type": "node", "id": 4005961975, "lat": 52.3122449, "lon": 4.9470883, "tags": {"name": "Amsterdam Bijlmer ArenA", "network": "NS;Amsterdamse metro", "network:subway": "Amsterdamse metro", "network:train": "NS", "old_name": "Amsterdam Bijlmer", "operator": "NS;GVB", "operator:subway": "GVB", "operator:train": "NS", "public_transport": "station", "railway": "station", "railway:ref": "Asb", "source": "AND", "start_date": "1971-05-24", "subway": "yes", "train": "yes", "wheelchair": "yes", "wikidata": "Q50723", "wikimedia_commons": "Category:Station Amsterdam Bijlmer ArenA", "wikipedia": "nl:Station Amsterdam Bijlmer ArenA", "zone": "5725"}}, {"type": "node", "id": 4040491812, "lat": 52.3464656, "lon": 4.9175567, "tags": {"addr:city": "Amsterdam", "addr:postcode": "1097DN", "addr:street": "Julianaplein", "name": "Amsterdam Amstel", "network": "Hoofdrailnet Nederland;Amsterdamse metro", "network:subway": "Amsterdamse metro", "network:train": "Hoofdrailnet Nederland", "operator": "Nederlandse Spoorwegen;GVB", "operator:subway": "GVB", "operator:train": "Nederlandse Spoorwegen", "public_transport": "station", "railway": "station", "railway:ref": "Asa", "start_date": "1939-10-15", "station": "train;subway", "subway": "yes", "train": "yes", "wheelchair": "limited", "wikidata": "Q50720", "wikimedia_commons": "Category:Amstelstation", "wikipedia": "nl:Station Amsterdam Amstel"}}, {"type": "node", "id": 4041640589, "lat": 52.296338, "lon": 4.9890129, "tags": {"name": "Gein", "network": "Amsterdamse metro", "operator": "GVB", "public_transport": "station", "railway": "station", "start_date": "1982-08-27", "station": "subway", "subway": "yes", "wikidata": "Q2331863", "wikipedia": "nl:Gein (metrostation)"}}, {"type": "node", "id": 4041640590, "lat": 52.2956478, "lon": 4.9744218, "tags": {"name": "Reigersbos", "network": "Amsterdamse metro", "operator": "GVB", "public_transport": "station", "railway": "station", "start_date": "1982-08-27", "station": "subway", "subway": "yes", "wheelchair": "yes", "wikidata": "Q1941199", "wikipedia": "nl:Reigersbos (metrostation)"}}, {"type": "node", "id": 4041642874, "lat": 52.3113175, "lon": 4.9843223, "tags": {"name": "Gaasperplas", "network": "Amsterdamse metro", "operator": "GVB", "public_transport": "station", "railway": "station", "start_date": "1977-10-14", "station": "subway", "subway": "yes", "wheelchair": "yes", "wikidata": "Q2187835", "wikimedia_commons": "Category:Metrostation Gaasperplas", "wikipedia": "nl:Gaasperplas (metrostation)", "zone": "5725"}}, {"type": "node", "id": 4041662264, "lat": 52.3230792, "lon": 4.9735502, "tags": {"name": "Ganzenhoef", "network": "Amsterdamse metro", "operator": "GVB", "public_transport": "station", "railway": "station", "start_date": "1977-10-14", "station": "subway", "subway": "yes", "wheelchair": "yes", "wikidata": "Q2534934", "wikimedia_commons": "Category:Metrostation Ganzenhoef", "wikipedia": "nl:Ganzenhoef (metrostation)", "zone": "5725"}}, {"type": "node", "id": 4041662265, "lat": 52.3170313, "lon": 4.9791233, "tags": {"name": "Kraaiennest", "network": "Amsterdamse metro", "operator": "GVB", "public_transport": "station", "railway": "station", "start_date": "1977-10-14", "station": "subway", "subway": "yes", "wheelchair": "yes", "wikidata": "Q3241211", "wikimedia_commons": "Category:Metrostation Kraaiennest", "wikipedia": "nl:Kraaiennest (metrostation)", "zone": "5725"}}, {"type": "node", "id": 4041664287, "lat": 52.3267669, "lon": 4.9463398, "tags": {"name": "Venserpolder", "network": "Amsterdamse metro", "operator": "GVB", "public_transport": "station", "railway": "station", "start_date": "1977-10-14", "station": "subway", "subway": "yes", "wheelchair": "yes", "wikidata": "Q3184721", "wikimedia_commons": "Category:Metrostation Venserpolder", "wikipedia": "nl:Venserpolder (metrostation)", "zone": "5715"}}, {"type": "node", "id": 4041666291, "lat": 52.3235787, "lon": 4.9365267, "tags": {"name": "Duivendrecht", "network": "Hoofdrailnet Nederland;Amsterdamse metro", "network:subway": "Amsterdamse metro", "network:train": "Hoofdrailnet Nederland", "operator": "Nederlandse Spoorwegen;GVB", "operator:subway": "GVB", "operator:train": "Nederlandse Spoorwegen", "public_transport": "station", "railway": "station", "railway:ref": "Dvd", "start_date": "1993-05-23", "station": "train;subway", "subway": "yes", "train": "yes", "wikidata": "Q49870", "wikimedia_commons": "Category:Station Duivendrecht", "wikipedia": "nl:Station Duivendrecht", "zone": "5715"}}, {"type": "node", "id": 4046323545, "lat": 52.3370349, "lon": 4.8902289, "tags": {"name": "Amsterdam RAI", "network": "Hoofdrailnet Nederland", "network:short": "HRN", "network:wikidata": "Q2337464", "network:wikipedia": "nl:Hoofdrailnet", "operator": "Nederlandse Spoorwegen", "public_transport": "station", "railway": "station", "railway:ref": "Rai", "start_date": "1981-05-31", "train": "yes", "website": "https://9292.nl/en/station-amsterdam-rai", "wheelchair": "yes", "wikidata": "Q512214", "wikimedia_commons": "Category:Station Amsterdam RAI", "wikipedia": "nl:Station Amsterdam RAI", "zone": "5714"}}, {"type": "node", "id": 4046383465, "lat": 52.3185355, "lon": 4.9413557, "tags": {"name": "Strandvliet", "network": "Amsterdamse metro", "operator": "GVB", "public_transport": "station", "railway": "station", "start_date": "1977-10-14", "station": "subway", "subway": "yes", "wikidata": "Q2181403", "wikimedia_commons": "Category:Metrostation Strandvliet", "wikipedia": "nl:Strandvliet (metrostation)"}}, {"type": "node", "id": 4046388677, "lat": 52.3066107, "lon": 4.9522364, "tags": {"name": "Bullewijk", "network": "Amsterdamse metro", "operator": "GVB", "public_transport": "station", "railway": "station", "start_date": "1977-10-14", "station": "subway", "subway": "yes", "wheelchair": "yes", "wikidata": "Q1986388", "wikimedia_commons": "Category:Metrostation Bullewijk", "wikipedia": "nl:Bullewijk (metrostation)"}}, {"type": "node", "id": 4053335995, "lat": 52.3524713, "lon": 4.8343026, "tags": {"departures_board": "realtime", "name": "Heemstedestraat", "network": "Amsterdamse metro", "operator": "GVB", "public_transport": "station", "railway": "station", "start_date": "1997-05-18", "station": "subway", "subway": "yes", "website": "https://9292.nl/en/amsterdam/metrostation-heemstedestraat", "wheelchair": "limited", "wikidata": "Q2287739", "wikimedia_commons": "Category:Metrostation Heemstedestraat", "wikipedia": "nl:Heemstedestraat (metrostation)"}}, {"type": "node", "id": 4064153245, "lat": 52.328939, "lon": 4.9662522, "tags": {"name": "Verrijn Stuartweg", "network": "Amsterdamse metro", "operator": "GVB", "public_transport": "station", "railway": "station", "start_date": "1977-10-14", "station": "subway", "subway": "yes", "wheelchair": "yes", "wikidata": "Q2593698", "wikimedia_commons": "Category:Metrostation Verrijn Stuartweg", "wikipedia": "nl:Verrijn Stuartweg (metrostation)"}}, {"type": "node", "id": 4073693626, "lat": 52.3399595, "lon": 4.9210115, "tags": {"name": "Spaklerweg", "network": "Amsterdamse metro", "operator": "GVB", "public_transport": "station", "railway": "station", "start_date": "1982-06-04", "station": "subway", "subway": "yes", "website": "https://9292.nl/en/amsterdam/metrostation-spaklerweg", "wheelchair": "yes", "wikidata": "Q3364889", "wikimedia_commons": "Category:Metrostation Spaklerweg", "wikipedia": "nl:Spaklerweg (metrostation)"}}, {"type": "node", "id": 4073693628, "lat": 52.3544624, "lon": 4.9120253, "tags": {"name": "Wibautstraat", "network": "Amsterdamse metro", "operator": "GVB", "public_transport": "station", "railway": "station", "start_date": "1977-10-14", "station": "subway", "subway": "yes", "wikidata": "Q3186873", "wikipedia": "nl:Wibautstraat (metrostation)"}}, {"type": "node", "id": 4073743506, "lat": 52.3713176, "lon": 4.9008788, "tags": {"name": "Nieuwmarkt", "name:de": "Neumarkt", "network": "Amsterdamse metro", "operator": "GVB", "public_transport": "station", "railway": "station", "start_date": "1980-10-11", "station": "subway", "subway": "yes", "wikidata": "Q1913095", "wikimedia_commons": "Category:Metrostation Nieuwmarkt", "wikipedia": "nl:Nieuwmarkt (metrostation)"}}, {"type": "node", "id": 4075987791, "lat": 52.3464029, "lon": 4.8345025, "tags": {"departures_board": "realtime", "departures_board:speech_output": "yes", "name": "Henk Sneevlietweg", "network": "Amsterdamse metro", "operator": "GVB", "public_transport": "station", "railway": "station", "start_date": "1997-05-18", "station": "subway", "subway": "yes", "website": "https://9292.nl/en/amsterdam/metrostation-henk-sneevlietweg", "wheelchair": "limited", "wikidata": "Q2751200", "wikimedia_commons": "Category:Metrostation Henk Sneevlietweg", "wikipedia": "nl:Henk Sneevlietweg (metrostation)"}}, {"type": "node", "id": 4076017504, "lat": 52.3578369, "lon": 4.8340268, "tags": {"addr:city": "Amsterdam", "addr:housenumber": "37", "addr:postcode": "1062HD", "addr:street": "Cornelis Lelylaan", "name": "Amsterdam Lelylaan", "network": "Hoofdrailnet Nederland;Amsterdamse metro", "network:subway": "Amsterdamse metro", "network:train": "Hoofdrailnet Nederland", "operator": "Nederlandse Spoorwegen;GVB", "operator:subway": "GVB", "operator:train": "Nederlandse Spoorwegen", "public_transport": "station", "railway": "station", "railway:ref": "Asdl", "start_date": "1986-06-01", "start_date:subway": "1997-05-28", "station": "train;subway", "subway": "yes", "train": "yes", "website": "https://9292.nl/station-amsterdam-lelylaan", "wheelchair": "yes", "wikidata": "Q50722", "wikimedia_commons": "Category:Station Amsterdam Lelylaan", "wikipedia": "nl:Station Amsterdam Lelylaan", "zone": "5713"}}, {"type": "node", "id": 4077313759, "lat": 52.3951713, "lon": 4.8507911, "tags": {"name": "Isolatorweg", "network": "Amsterdamse metro", "operator": "GVB", "public_transport": "station", "railway": "station", "start_date": "1997-05-28", "station": "subway", "subway": "yes", "wheelchair": "yes", "wikidata": "Q2146949", "wikipedia": "nl:Isolatorweg (metrostation)"}}, {"type": "node", "id": 4077313763, "lat": 52.3642921, "lon": 4.8339612, "tags": {"alt_name": "Metrostation Postjesweg", "name": "Postjesweg", "network": "Amsterdamse metro", "operator": "GVB", "public_transport": "station", "railway": "station", "start_date": "1997-05-28", "station": "subway", "subway": "yes", "website": "https://9292.nl/en/amsterdam/metrostation-postjesweg", "wheelchair": "yes", "wikidata": "Q2436525", "wikimedia_commons": "Category:Metrostation Postjesweg", "wikipedia": "nl:Postjesweg (metrostation)"}}, {"type": "node", "id": 4144568336, "lat": 52.2785602, "lon": 4.9773816, "tags": {"name": "Abcoude", "public_transport": "station", "railway": "station", "railway:ref": "Ac", "source": "AND", "train": "yes", "wheelchair": "yes", "wikidata": "Q1893105", "wikipedia": "nl:Station Abcoude", "zone": "5735"}}, {"type": "node", "id": 4290854847, "lat": 52.378901, "lon": 4.9005805, "tags": {"alt_name": "Amsterdam Centraal Station", "internet_access": "no", "name": "Amsterdam Centraal", "name:de": "Amsterdam Hauptbahnhof", "name:el": "\u039a\u03b5\u03bd\u03c4\u03c1\u03b9\u03ba\u03cc\u03c2 \u03c3\u03c4\u03b1\u03b8\u03bc\u03cc\u03c2 \u0386\u03bc\u03c3\u03c4\u03b5\u03c1\u03bd\u03c4\u03b1\u03bc", "name:en": "Amsterdam Central Station", "name:es": "Estaci\u00f3n Central de \u00c1msterdam", "name:fr": "Gare centrale d'Amsterdam", "name:ja": "\u30a2\u30e0\u30b9\u30c6\u30eb\u30c0\u30e0\u4e2d\u592e\u99c5", "name:ko": "\uc554\uc2a4\ud14c\ub974\ub2f4 \uc911\uc559\uc5ed", "name:nl": "Amsterdam Centraal", "name:zh": "\u963f\u59c6\u65af\u7279\u4e39\u4e2d\u592e\u8f66\u7ad9", "name:zh-Hant": "\u963f\u59c6\u65af\u7279\u4e39\u4e2d\u592e\u8eca\u7ad9", "old_name:-2000-05-29": "Amsterdam CS", "operator": "NS", "public_transport": "station", "railway": "station", "railway:ref": "Asd", "railway:ref:DB": "XNAC", "railway:ref:NMBS/SNCB": "XNASD", "start_date": "1889-10-15", "train": "yes", "uic_ref": "8400058", "wheelchair": "yes", "wikidata": "Q50719", "wikipedia": "nl:Station Amsterdam Centraal", "zone": "5700"}}, {"type": "node", "id": 4487548898, "lat": 52.3608341, "lon": 4.9311934, "tags": {"alt_name": "Muiderpoortstation", "name": "Amsterdam Muiderpoort", "public_transport": "station", "railway": "station", "railway:ref": "Asdm", "train": "yes", "wheelchair": "yes", "wikidata": "Q50724", "wikimedia_commons": "Category:Muiderpoortstation", "wikipedia": "nl:Station Amsterdam Muiderpoort"}}, {"type": "node", "id": 5252944882, "lat": 52.3390172, "lon": 4.8734324, "tags": {"addr:city": "Amsterdam", "addr:country": "NL", "addr:housenumber": "10", "addr:street": "Zuidplein", "name": "Amsterdam Zuid", "network": "Hoofdrailnet Nederland", "network:short": "HRN", "network:wikidata": "Q2337464", "network:wikipedia": "nl:Hoofdrailnet", "old_name:1985-2006": "Amsterdam Zuid-WTC", "operator": "Nederlandse Spoorwegen", "public_transport": "station", "railway": "station", "railway:ref": "Asdz", "source": "BAG", "source:date": "2014-03-24", "start_date": "1978-12-21", "train": "yes", "website": "https://www.ns.nl/stationsinformatie/amsterdam-zuid.html", "wheelchair": "yes", "wikidata": "Q49872", "wikimedia_commons": "Category:Station Amsterdam Zuid", "wikipedia": "nl:Station Amsterdam Zuid"}}, {"type": "node", "id": 5267675295, "lat": 52.3392032, "lon": 4.8746127, "tags": {"name": "Zuid", "network": "Amsterdamse metro", "operator": "Gemeentelijk Vervoerbedrijf", "public_transport": "station", "railway": "station", "start_date": "1990-12-01", "station": "subway", "subway": "yes", "website": "https://9292.nl/en/station-amsterdam-zuid?tab=subway", "wheelchair": "yes", "wikidata": "Q105083608", "wikimedia_commons": "Category:Metrostation Amsterdam Zuid", "wikipedia": "nl:Station Amsterdam Zuid"}}, {"type": "node", "id": 5267675296, "lat": 52.3890161, "lon": 4.838877, "tags": {"name": "Station Sloterdijk", "network": "Amsterdamse metro", "operator": "GVB", "public_transport": "station", "railway": "station", "start_date": "1997-05-28", "station": "subway", "subway": "yes", "wikidata": "Q50721", "wikipedia": "nl:Station Amsterdam Sloterdijk"}}, {"type": "node", "id": 5360384018, "lat": 52.3377124, "lon": 4.8893261, "tags": {"name": "Station RAI", "network": "Amsterdamse metro", "operator": "GVB", "public_transport": "station", "railway": "station", "start_date": "1990-12-01", "station": "subway", "subway": "yes", "wikidata": "Q512214", "wikipedia": "nl:Station Amsterdam RAI"}}, {"type": "node", "id": 5424713348, "lat": 52.3774316, "lon": 4.9009578, "tags": {"name": "Centraal Station", "name:de": "Hauptbahnhof", "network": "Amsterdamse metro", "operator": "GVB", "public_transport": "station", "railway": "station", "start_date": "1980-10-11", "station": "subway", "subway": "yes", "toilets:wheelchair": "yes", "wheelchair": "yes"}}, {"type": "node", "id": 5737467956, "lat": 52.3416064, "lon": 4.8914727, "tags": {"layer": "-2", "name": "Europaplein", "name:de": "Europaplatz", "network": "Amsterdamse metro", "operator": "Gemeentelijk Vervoerbedrijf", "public_transport": "station", "railway": "station", "start_date": "2018-07-21", "station": "subway", "subway": "yes", "wheelchair": "yes", "wikidata": "Q2875188", "wikimedia_commons": "Category:Metrostation Europaplein", "wikipedia": "nl:Europaplein (metrostation)"}}, {"type": "node", "id": 5737467957, "lat": 52.3539754, "lon": 4.8906926, "tags": {"name": "De Pijp", "network": "Amsterdamse metro", "operator": "GVB", "public_transport": "station", "railway": "station", "start_date": "2018-07-21", "station": "subway", "subway": "yes", "wikidata": "Q2501300", "wikipedia": "nl:De Pijp (metrostation)"}}, {"type": "node", "id": 5737467958, "lat": 52.3608169, "lon": 4.8911646, "tags": {"name": "Vijzelgracht", "network": "Amsterdamse metro", "operator": "GVB", "public_transport": "station", "railway": "station", "start_date": "2018-07-21", "station": "subway", "subway": "yes", "website": "https://9292.nl/en/amsterdam/metrostation-vijzelgracht", "wheelchair": "yes", "wikidata": "Q2722265", "wikimedia_commons": "Category:Metrostation Vijzelgracht", "wikipedia": "nl:Vijzelgracht (metrostation)"}}, {"type": "node", "id": 5737467960, "lat": 52.3889316, "lon": 4.9187004, "tags": {"name": "Noorderpark", "network": "Amsterdamse metro", "operator": "GVB", "public_transport": "station", "railway": "station", "start_date": "2018-07-21", "station": "subway", "subway": "yes", "wheelchair": "yes", "wikidata": "Q2673118", "wikimedia_commons": "Category:Metrostation Noorderpark", "wikipedia": "nl:Noorderpark (metrostation)"}}, {"type": "node", "id": 5737467961, "lat": 52.4019931, "lon": 4.9323589, "tags": {"name": "Noord", "network": "Amsterdamse metro", "old_name": "Buikslotermeerplein", "operator": "GVB", "public_transport": "station", "railway": "station", "start_date": "2018-07-21", "station": "subway", "subway": "yes", "toilets:wheelchair": "no", "wheelchair": "yes", "wikidata": "Q3007607", "wikipedia": "nl:Noord (metrostation)"}}, {"type": "node", "id": 6757261128, "lat": 52.3697494, "lon": 4.8926815}, {"type": "node", "id": 7606648991, "lat": 52.3122067, "lon": 5.0440484, "tags": {"name": "Weesp", "public_transport": "station", "railway": "station", "railway:ref": "Wp", "train": "yes", "wheelchair": "limited", "wikidata": "Q801585", "wikipedia": "nl:Station Weesp", "zone": "5820"}}, {"type": "node", "id": 7606648992, "lat": 52.352926, "lon": 4.948315, "tags": {"name": "Amsterdam Science Park", "public_transport": "station", "railway": "station", "railway:ref": "Assp", "train": "yes", "wheelchair": "yes", "wikidata": "Q2102286", "wikimedia_commons": "Category:Station Amsterdam Science Park", "wikipedia": "nl:Station Amsterdam Science Park"}}, {"type": "node", "id": 7606698742, "lat": 52.3452067, "lon": 4.967465, "tags": {"name": "Diemen", "public_transport": "station", "railway": "station", "railway:ref": "Dmn", "train": "yes", "wheelchair": "yes", "wikidata": "Q2692686", "wikimedia_commons": "Category:Station Diemen", "wikipedia": "nl:Station Diemen", "zone": "5715"}}, {"type": "node", "id": 9167352325, "lat": 52.3791977, "lon": 4.9009058, "tags": {"alt_name": "Amsterdam Centraal Station", "layer": "-3", "name": "Centraal Station", "operator": "Gemeentelijk Vervoerbedrijf", "public_transport": "station", "railway": "station", "station": "subway", "subway": "yes", "wheelchair": "yes"}}, {"type": "way", "id": 266903916, "nodes": [2724002516, 2724002359, 2724002225, 2724002236, 2724002244, 2724002257, 2724002259, 2724002497, 2724002498, 2724002623, 2724002690, 2724002697, 2724002844, 2724002939, 2724003506, 2724003683, 2724003710, 2724004022, 2724004020, 2724004222, 2724004202, 3187687707, 2724004294, 2724004400, 2724004383, 2724004341, 2724004340, 2724004150, 2724004095, 2724003898, 2724003901, 2724003791, 2724003678, 2724003394, 2724003266, 2724002903, 2724002849, 2724002705, 6757261128, 2724002515, 2724002516], "tags": {"building:part": "yes", "layer": "-2", "location": "underground", "name": "Rokin", "network": "Amsterdamse metro", "operator": "Gemeentelijk Vervoerbedrijf", "public_transport": "station", "railway": "station", "ref:bag": "0363100012240258", "source": "BAG", "source:date": "2014-02-11", "start_date": "2018", "station": "subway", "subway": "yes", "wheelchair": "yes"}}, {"type": "way", "id": 268782305, "nodes": [2741068589, 2741068626, 2741068607, 2741068657, 2741068660, 2741068664, 2741068658, 2741068665, 2741068671, 2741068678, 2741068680, 2741068673, 2741068651, 2741068654, 2741068649, 2741068528, 2741068425, 2741068324, 2741068427, 2741068412, 2741068406, 2741068312, 2741068383, 2741068392, 2741068396, 2741068405, 2741068410, 2741068464, 2741068580, 2741068535, 2741068546, 2741068574, 2741068589], "tags": {"addr:city": "Amsterdam", "addr:postcode": "1011RL", "layer": "-1", "level": "-1", "name": "Waterlooplein", "name:de": "Waterlooplatz", "network": "Amsterdamse metro", "operator": "Gemeentelijk Vervoerbedrijf", "public_transport": "station", "railway": "station", "ref:bag": "363100012164935", "source": "BAG", "source:date": "2014-03-24", "start_date": "1980-10-11", "station": "subway", "subway": "yes", "wikidata": "Q2486332", "wikipedia": "nl:Waterlooplein (metrostation)"}}, {"type": "way", "id": 268998785, "nodes": [2742814540, 2742815082, 2742815177, 2742815411, 2742815421, 2742815426, 2742815434, 2742815439, 2742815443, 2742815455, 2742815479, 2742815488, 2742815531, 2742815618, 2742815610, 2742815591, 2742815583, 2742815587, 2742815680, 2742816312, 2742816574, 2742816181, 2742816349, 2742816228, 2742816225, 2742815845, 2742815816, 2742815748, 2742815750, 2742815661, 2742815627, 2742814073, 2742813976, 2742813885, 2742813925, 2742814210, 2742814310, 2742814128, 2742814079, 2742814005, 2742813954, 2742813991, 2742813782, 2742813779, 2742813777, 2742813792, 2742813775, 2742813765, 2742813727, 2742813796, 2742813791, 2742813620, 2742813608, 2742813602, 2742813672, 2742813681, 2742813678, 2742813673, 2742813574, 2742813526, 2742813506, 2742813460, 2742813501, 2742813471, 2742813509, 2742813508, 2742813517, 2742813537, 2742813545, 2742813538, 2742813843, 2742813814, 2742814315, 2742814262, 2742814253, 2742814247, 2742814244, 2742814241, 2742814235, 2742814222, 2742814202, 2742814184, 2742813969, 2742813965, 2742813961, 2742813956, 2742813950, 2742813945, 2742813941, 2742813936, 2742813933, 2742813911, 2742813957, 2742813975, 2742813977, 2742813981, 2742813983, 2742813989, 2742814232, 2742814268, 2742814290, 2742814308, 2742814321, 2742814324, 2742814332, 2742814338, 2742814629, 2742814640, 2742814993, 2742815001, 2742814997, 2742814540], "tags": {"building": "yes", "layer": "-1", "level": "-1", "location": "underground", "name": "Weesperplein", "network": "Amsterdamse metro", "operator": "Gemeentelijk Vervoerbedrijf", "public_transport": "station", "railway": "station", "ref:bag": "0363100012186191", "source": "BAG", "source:date": "2014-03-24", "start_date": "1977", "station": "subway", "subway": "yes", "wheelchair": "yes", "wikidata": "Q7979626", "wikimedia_commons": "File:Weesperplein amsterdam.jpg", "wikipedia": "nl:Weesperplein (metrostation)"}}]}